azure/mgmt/securityinsight/__init__.py
azure/mgmt/securityinsight/_configuration.py
azure/mgmt/securityinsight/_patch.py
azure/mgmt/securityinsight/_security_insights.py
azure/mgmt/securityinsight/_vendor.py
azure/mgmt/securityinsight/_version.py
azure/mgmt/securityinsight/py.typed
azure/mgmt/securityinsight/aio/__init__.py
azure/mgmt/securityinsight/aio/_configuration.py
azure/mgmt/securityinsight/aio/_patch.py
azure/mgmt/securityinsight/aio/_security_insights.py
azure/mgmt/securityinsight/aio/operations/__init__.py
azure/mgmt/securityinsight/aio/operations/_actions_operations.py
azure/mgmt/securityinsight/aio/operations/_alert_rule_templates_operations.py
azure/mgmt/securityinsight/aio/operations/_alert_rules_operations.py
azure/mgmt/securityinsight/aio/operations/_automation_rules_operations.py
azure/mgmt/securityinsight/aio/operations/_bookmarks_operations.py
azure/mgmt/securityinsight/aio/operations/_data_connectors_operations.py
azure/mgmt/securityinsight/aio/operations/_incident_comments_operations.py
azure/mgmt/securityinsight/aio/operations/_incident_relations_operations.py
azure/mgmt/securityinsight/aio/operations/_incidents_operations.py
azure/mgmt/securityinsight/aio/operations/_operations.py
azure/mgmt/securityinsight/aio/operations/_patch.py
azure/mgmt/securityinsight/aio/operations/_sentinel_onboarding_states_operations.py
azure/mgmt/securityinsight/aio/operations/_threat_intelligence_indicator_metrics_operations.py
azure/mgmt/securityinsight/aio/operations/_threat_intelligence_indicator_operations.py
azure/mgmt/securityinsight/aio/operations/_threat_intelligence_indicators_operations.py
azure/mgmt/securityinsight/aio/operations/_watchlist_items_operations.py
azure/mgmt/securityinsight/aio/operations/_watchlists_operations.py
azure/mgmt/securityinsight/models/__init__.py
azure/mgmt/securityinsight/models/_models_py3.py
azure/mgmt/securityinsight/models/_patch.py
azure/mgmt/securityinsight/models/_security_insights_enums.py
azure_mgmt_securityinsight-1.0.0.dist-info/LICENSE
azure_mgmt_securityinsight-1.0.0.dist-info/METADATA
azure_mgmt_securityinsight-1.0.0.dist-info/WHEEL
azure_mgmt_securityinsight-1.0.0.dist-info/top_level.txt
azure_mgmt_securityinsight-1.0.0.dist-info/RECORD
